bioinfo_parser/__init__.py
bioinfo_parser/bioinfo_parser.py
shinejh0528_bioinfo_parser-0.0.4.dist-info/LICENSE.txt
shinejh0528_bioinfo_parser-0.0.4.dist-info/METADATA
shinejh0528_bioinfo_parser-0.0.4.dist-info/WHEEL
shinejh0528_bioinfo_parser-0.0.4.dist-info/top_level.txt
shinejh0528_bioinfo_parser-0.0.4.dist-info/RECORD
