Metadata-Version: 2.1
Name: shinejh0528-bioinfo-parser
Version: 0.0.4
Summary: Bioinfomatics parser
Home-page: https://github.com/Shin-jongwhan/python_pypi/tree/main/bioinfo_parser
Author: Jonghwan Shin
Author-email: shinejh0528@gmail.com
License: UNKNOWN
Platform: UNKNOWN
Classifier: Programming Language :: Python :: 3
Classifier: License :: OSI Approved :: MIT License
Classifier: Operating System :: OS Independent
Requires-Python: >=3.6
